{
    "fluentMethods": true,
    "clientRootFolder": "",
    "relationships": [
        {
            "relationshipName": "user",
            "otherEntityName": "user",
            "relationshipType": "one-to-one",
            "relationshipValidateRules": [
                "required"
            ],
            "otherEntityField": "login",
            "ownerSide": true,
            "otherEntityRelationshipName": "usuario"
        },
        {
            "relationshipName": "persona",
            "otherEntityName": "persona",
            "relationshipType": "one-to-one",
            "relationshipValidateRules": [
                "required"
            ],
            "otherEntityField": "id",
            "ownerSide": true,
            "otherEntityRelationshipName": "usuario"
        }
    ],
    "fields": [
        {
            "fieldName": "cargo",
            "fieldType": "String",
            "fieldValidateRules": [
                "required"
            ]
        }
    ],
    "changelogDate": "20180819072647",
    "dto": "no",
    "searchEngine": false,
    "service": "serviceImpl",
    "entityTableName": "usuario",
    "jpaMetamodelFiltering": false,
    "pagination": "pagination"
}
